weather4py/__init__.py
weather4py-0.1.4.dist-info/WHEEL
weather4py-0.1.4.dist-info/METADATA
weather4py-0.1.4.dist-info/RECORD
