Metadata-Version: 2.1
Name: weather4py
Version: 0.1.4
Summary: a library for your weathery needs.
Author: MintTeaNeko
Author-email: neonwinternight1@gmail.com
Requires-Python: >=3.10,<4.0
Classifier: Programming Language :: Python :: 3
Classifier: Programming Language :: Python :: 3.10
Requires-Dist: requests (>=2.28.1,<3.0.0)
